74381/alu_74381.v
`define OPERATION_CLEAR      3'b000
`define OPERATION_B_MINUS_A  3'b001
`define OPERATION_A_MINUS_B  3'b010
`define OPERATION_A_PLUS_B   3'b011
`define OPERATION_A_XOR_B    3'b100
`define OPERATION_A_OR_B     3'b101
`define OPERATION_A_AND_B    3'b110
`define OPERATION_PRESENT    3'b111

module alu_74381 (
    input wire [3:0] A,
    input wire [3:0] B,
    input wire [2:0] S,
    input wire Cn,
    output reg [3:0] F,
    output wire P, G
  );

  reg [3:0] P_int;
  reg [3:0] G_int;

  assign P = ~(&P_int);
  assign G = ~(G_int[3] | (P_int[3] & G_int[2]) | (P_int[3] & P_int[2] & G_int[1]) | (P_int[3] & P_int[2] & P_int[1] & G_int[0]));

  always @ (*)
  begin
    case (S)
      `OPERATION_CLEAR:
      begin
        F = 0;
        P_int = 4'b1111;
        G_int = 4'b1111;
      end
      `OPERATION_B_MINUS_A:
      begin
        F = B + ~A + {3'b0,Cn};
        P_int = (~A) | B;
        G_int = (~A) & B;
      end
      `OPERATION_A_MINUS_B:
      begin
        F = ~B + A + {3'b0,Cn};
        P_int = A | ~B;
        G_int = A & ~B;
      end
      `OPERATION_A_PLUS_B:
      begin
        F = A + B + {3'b0,Cn};
        P_int = A | B;
        G_int = (A) & B;
      end
      `OPERATION_A_XOR_B:
      begin
        F = A ^ B;
        if(A == 0 & B == 4'b1111)
        begin
          P_int = 0;
        end
        else
          P_int = A | B;
        G_int = (A) & B;
      end
      `OPERATION_A_OR_B:
      begin
        F = A | B;
        if((A == 4'b1111) & (B == 4'b1111))
        begin
          P_int = 4'b1111;
        end
        else
          P_int = 4'b0000;
        G_int = 4'b0000;
      end
      `OPERATION_A_AND_B:
      begin
        F = A & B;
        if(((A == 4'b0000) & (B == 4'b0000)) || ((A == 4'b1111) & (B == 4'b0000)) )
        begin
          P_int = 4'b1111;
          G_int = 4'b1111;
        end
        else if ((B == 4'b1111) & (A == 4'b0000))
        begin
          P_int = 4'b0000;
          G_int = 4'b0000;
        end
        else
        begin
          P_int = 4'b1111;
          G_int = 4'b0000;
        end
      end
      `OPERATION_PRESENT:
      begin
        F = 4'b1111;
        if((A == 4'b1111) & (B == 4'b1111))
        begin
          P_int = 4'b1111;
        end
        else
          P_int = 4'b0000;
        G_int = 4'b0000;
      end
      default:
        F = 4'b0000;
    endcase
  end

endmodule

74381/16_bit/alu_16_bit.v
module alu_16_bit (
    input wire [15:0] A,
    input wire [15:0] B,
    input wire [2:0] S,
    input wire Cn,
    output wire [15:0] F,
    // output wire P, G
    output wire Co

  );

  wire [3:0] F0, F1, F2, F3;
  wire P0, P1, P2, P3;
  wire G0, G1, G2, G3;
  wire Cn1, Cn2, Cn3;

  alu_74381 alu0 (
              .A(A[3:0]),
              .B(B[3:0]),
              .S(S),
              .Cn(Cn),
              .F(F0),
              .P(P0),
              .G(G0)
            );

  alu_74381 alu1 (
              .A(A[7:4]),
              .B(B[7:4]),
              .S(S),
              .Cn(Cn1),
              .F(F1),
              .P(P1),
              .G(G1)
            );

  alu_74381 alu2 (
              .A(A[11:8]),
              .B(B[11:8]),
              .S(S),
              .Cn(Cn2),
              .F(F2),
              .P(P2),
              .G(G2)
            );

  alu_74381 alu3 (
              .A(A[15:12]),
              .B(B[15:12]),
              .S(S),
              .Cn(Cn3),
              .F(F3),
              .P(P3),
              .G(G3)
            );

  assign F = {F3, F2, F1, F0};

  assign Cn1 = ~G0 | (~P0 & Cn);
  assign Cn2 = ~G1 | (~P1 & Cn1);
  assign Cn3 = ~G2 | (~P2 & Cn2);
  assign Co =  ~G3 | (~P3 & Cn3);





  //   assign P = P3 & P2 & P1 & P0;
  //   assign G = G3 | (P3 & G2) | (P3 & P2 & G1) | (P3 & P2 & P1 & G0);

endmodule

74381/16_bit/adder16.vcd
$version Generated by VerilatedVcd $end
$timescale 1ps $end
 $scope module TOP $end
  $var wire 16 : A [15:0] $end
  $var wire 16 ; B [15:0] $end
  $var wire 3 < S [2:0] $end
  $var wire 1 = Cn $end
  $var wire 16 > F [15:0] $end
  $var wire 1 ? Co $end
  $scope module alu_16_bit $end
   $var wire 16 : A [15:0] $end
   $var wire 16 ; B [15:0] $end
   $var wire 3 < S [2:0] $end
   $var wire 1 = Cn $end
   $var wire 16 > F [15:0] $end
   $var wire 1 ? Co $end
   $var wire 4 # F0 [3:0] $end
   $var wire 4 $ F1 [3:0] $end
   $var wire 4 % F2 [3:0] $end
   $var wire 4 & F3 [3:0] $end
   $var wire 1 ' P0 $end
   $var wire 1 ( P1 $end
   $var wire 1 ) P2 $end
   $var wire 1 * P3 $end
   $var wire 1 + G0 $end
   $var wire 1 , G1 $end
   $var wire 1 - G2 $end
   $var wire 1 . G3 $end
   $var wire 1 / Cn1 $end
   $var wire 1 0 Cn2 $end
   $var wire 1 1 Cn3 $end
   $scope module alu0 $end
    $var wire 4 @ A [3:0] $end
    $var wire 4 A B [3:0] $end
    $var wire 3 < S [2:0] $end
    $var wire 1 = Cn $end
    $var wire 4 # F [3:0] $end
    $var wire 1 ' P $end
    $var wire 1 + G $end
    $var wire 4 2 P_int [3:0] $end
    $var wire 4 3 G_int [3:0] $end
   $upscope $end
   $scope module alu1 $end
    $var wire 4 B A [3:0] $end
    $var wire 4 C B [3:0] $end
    $var wire 3 < S [2:0] $end
    $var wire 1 / Cn $end
    $var wire 4 $ F [3:0] $end
    $var wire 1 ( P $end
    $var wire 1 , G $end
    $var wire 4 4 P_int [3:0] $end
    $var wire 4 5 G_int [3:0] $end
   $upscope $end
   $scope module alu2 $end
    $var wire 4 D A [3:0] $end
    $var wire 4 E B [3:0] $end
    $var wire 3 < S [2:0] $end
    $var wire 1 0 Cn $end
    $var wire 4 % F [3:0] $end
    $var wire 1 ) P $end
    $var wire 1 - G $end
    $var wire 4 6 P_int [3:0] $end
    $var wire 4 7 G_int [3:0] $end
   $upscope $end
   $scope module alu3 $end
    $var wire 4 F A [3:0] $end
    $var wire 4 G B [3:0] $end
    $var wire 3 < S [2:0] $end
    $var wire 1 1 Cn $end
    $var wire 4 & F [3:0] $end
    $var wire 1 * P $end
    $var wire 1 . G $end
    $var wire 4 8 P_int [3:0] $end
    $var wire 4 9 G_int [3:0] $end
   $upscope $end
  $upscope $end
 $upscope $end
$enddefinitions $end


#0
b0000 #
b0000 $
b0000 %
b0000 &
1'
1(
1)
1*
1+
1,
1-
1.
0/
00
01
b0000 2
b0000 3
b0000 4
b0000 5
b0000 6
b0000 7
b0000 8
b0000 9
b0000000000000000 :
b0000000000000000 ;
b011 <
0=
b0000000000000000 >
0?
b0000 @
b0000 A
b0000 B
b0000 C
b0000 D
b0000 E
b0000 F
b0000 G
#1
b0001 #
1=
b0000000000000001 >
#2
b0001 2
b0000000000000001 ;
0=
b0001 A
#3
b0010 #
1=
b0000000000000010 >
#4
b0010 2
b0000000000000010 ;
0=
b0010 A
#5
b0011 #
1=
b0000000000000011 >
#6
b0011 2
b0000000000000011 ;
0=
b0011 A
#7
b0100 #
1=
b0000000000000100 >
#8
b0100 2
b0000000000000100 ;
0=
b0100 A
#9
b0101 #
1=
b0000000000000101 >
#10
b0101 2
b0000000000000101 ;
0=
b0101 A
#11
b0110 #
1=
b0000000000000110 >
#12
b0110 2
b0000000000000110 ;
0=
b0110 A
#13
b0111 #
1=
b0000000000000111 >
#14
b0111 2
b0000000000000111 ;
0=
b0111 A
#15
b1000 #
1=
b0000000000001000 >
#16
b1000 2
b0000000000001000 ;
0=
b1000 A
#17
b1001 #
1=
b0000000000001001 >
#18
b1001 2
b0000000000001001 ;
0=
b1001 A
#19
b1010 #
1=
b0000000000001010 >
#20
b1010 2
b0000000000001010 ;
0=
b1010 A
#21
b1011 #
1=
b0000000000001011 >
#22
b1011 2
b0000000000001011 ;
0=
b1011 A
#23
b1100 #
1=
b0000000000001100 >
#24
b1100 2
b0000000000001100 ;
0=
b1100 A
#25
b1101 #
1=
b0000000000001101 >
#26
b1101 2
b0000000000001101 ;
0=
b1101 A
#27
b1110 #
1=
b0000000000001110 >
#28
b1110 2
b0000000000001110 ;
0=
b1110 A
#29
b1111 #
1=
b0000000000001111 >
#30
0'
b1111 2
b0000000000001111 ;
0=
b1111 A
#31
b0000 #
b0001 $
1/
1=
b0000000000010000 >
#32
1'
0/
b0000 2
b0001 4
b0000000000010000 ;
0=
b0000 A
b0001 C
#33
b0001 #
1=
b0000000000010001 >
#34
b0001 2
b0000000000010001 ;
0=
b0001 A
#35
b0010 #
1=
b0000000000010010 >
#36
b0010 2
b0000000000010010 ;
0=
b0010 A
#37
b0011 #
1=
b0000000000010011 >
#38
b0011 2
b0000000000010011 ;
0=
b0011 A
#39
b0100 #
1=
b0000000000010100 >
#40
b0100 2
b0000000000010100 ;
0=
b0100 A
#41
b0101 #
1=
b0000000000010101 >
#42
b0101 2
b0000000000010101 ;
0=
b0101 A
#43
b0110 #
1=
b0000000000010110 >
#44
b0110 2
b0000000000010110 ;
0=
b0110 A
#45
b0111 #
1=
b0000000000010111 >
#46
b0111 2
b0000000000010111 ;
0=
b0111 A
#47
b1000 #
1=
b0000000000011000 >
#48
b1000 2
b0000000000011000 ;
0=
b1000 A
#49
b1001 #
1=
b0000000000011001 >
#50
b1001 2
b0000000000011001 ;
0=
b1001 A
#51
b1010 #
1=
b0000000000011010 >
#52
b1010 2
b0000000000011010 ;
0=
b1010 A
#53
b1011 #
1=
b0000000000011011 >
#54
b1011 2
b0000000000011011 ;
0=
b1011 A
#55
b1100 #
1=
b0000000000011100 >
#56
b1100 2
b0000000000011100 ;
0=
b1100 A
#57
b1101 #
1=
b0000000000011101 >
#58
b1101 2
b0000000000011101 ;
0=
b1101 A
#59
b1110 #
1=
b0000000000011110 >
#60
b1110 2
b0000000000011110 ;
0=
b1110 A
#61
b1111 #
1=
b0000000000011111 >
#62
0'
b1111 2
b0000000000011111 ;
0=
b1111 A
#63
b0000 #
b0010 $
1/
1=
b0000000000100000 >
#64
1'
0/
b0000 2
b0010 4
b0000000000100000 ;
0=
b0000 A
b0010 C
#65
b0001 #
1=
b0000000000100001 >
#66
b0001 2
b0000000000100001 ;
0=
b0001 A
#67
b0010 #
1=
b0000000000100010 >
#68
b0010 2
b0000000000100010 ;
0=
b0010 A
#69
b0011 #
1=
b0000000000100011 >
#70
b0011 2
b0000000000100011 ;
0=
b0011 A
#71
b0100 #
1=
b0000000000100100 >
#72
b0100 2
b0000000000100100 ;
0=
b0100 A
#73
b0101 #
1=
b0000000000100101 >
#74
b0101 2
b0000000000100101 ;
0=
b0101 A
#75
b0110 #
1=
b0000000000100110 >
#76
b0110 2
b0000000000100110 ;
0=
b0110 A
#77
b0111 #
1=
b0000000000100111 >
#78
b0111 2
b0000000000100111 ;
0=
b0111 A
#79
b1000 #
1=
b0000000000101000 >
#80
b1000 2
b0000000000101000 ;
0=
b1000 A
#81
b1001 #
1=
b0000000000101001 >
#82
b1001 2
b0000000000101001 ;
0=
b1001 A
#83
b1010 #
1=
b0000000000101010 >
#84
b1010 2
b0000000000101010 ;
0=
b1010 A
#85
b1011 #
1=
b0000000000101011 >
#86
b1011 2
b0000000000101011 ;
0=
b1011 A
#87
b1100 #
1=
b0000000000101100 >
#88
b1100 2
b0000000000101100 ;
0=
b1100 A
#89
b1101 #
1=
b0000000000101101 >
#90
b1101 2
b0000000000101101 ;
0=
b1101 A
#91
b1110 #
1=
b0000000000101110 >
#92
b1110 2
b0000000000101110 ;
0=
b1110 A
#93
b1111 #
1=
b0000000000101111 >
#94
0'
b1111 2
b0000000000101111 ;
0=
b1111 A
#95
b0000 #
b0011 $
1/
1=
b0000000000110000 >
#96
1'
0/
b0000 2
b0011 4
b0000000000110000 ;
0=
b0000 A
b0011 C
#97
b0001 #
1=
b0000000000110001 >
#98
b0001 2
b0000000000110001 ;
0=
b0001 A
#99
b0010 #
1=
b0000000000110010 >
#100
b0010 2
b0000000000110010 ;
0=
b0010 A
#101
b0011 #
1=
b0000000000110011 >
#102
b0011 2
b0000000000110011 ;
0=
b0011 A
#103
b0100 #
1=
b0000000000110100 >
#104
b0100 2
b0000000000110100 ;
0=
b0100 A
#105
b0101 #
1=
b0000000000110101 >
#106
b0101 2
b0000000000110101 ;
0=
b0101 A
#107
b0110 #
1=
b0000000000110110 >
#108
b0110 2
b0000000000110110 ;
0=
b0110 A
#109
b0111 #
1=
b0000000000110111 >
#110
b0111 2
b0000000000110111 ;
0=
b0111 A
#111
b1000 #
1=
b0000000000111000 >
#112
b1000 2
b0000000000111000 ;
0=
b1000 A
#113
b1001 #
1=
b0000000000111001 >
#114
b1001 2
b0000000000111001 ;
0=
b1001 A
#115
b1010 #
1=
b0000000000111010 >
#116
b1010 2
b0000000000111010 ;
0=
b1010 A
#117
b1011 #
1=
b0000000000111011 >
#118
b1011 2
b0000000000111011 ;
0=
b1011 A
#119
b1100 #
1=
b0000000000111100 >
#120
b1100 2
b0000000000111100 ;
0=
b1100 A
#121
b1101 #
1=
b0000000000111101 >
#122
b1101 2
b0000000000111101 ;
0=
b1101 A
#123
b1110 #
1=
b0000000000111110 >
#124
b1110 2
b0000000000111110 ;
0=
b1110 A
#125
b1111 #
1=
b0000000000111111 >
#126
0'
b1111 2
b0000000000111111 ;
0=
b1111 A
#127
b0000 #
b0100 $
1/
1=
b0000000001000000 >
#128
1'
0/
b0000 2
b0100 4
b0000000001000000 ;
0=
b0000 A
b0100 C
#129
b0001 #
1=
b0000000001000001 >
#130
b0001 2
b0000000001000001 ;
0=
b0001 A
#131
b0010 #
1=
b0000000001000010 >
#132
b0010 2
b0000000001000010 ;
0=
b0010 A
#133
b0011 #
1=
b0000000001000011 >
#134
b0011 2
b0000000001000011 ;
0=
b0011 A
#135
b0100 #
1=
b0000000001000100 >
#136
b0100 2
b0000000001000100 ;
0=
b0100 A
#137
b0101 #
1=
b0000000001000101 >
#138
b0101 2
b0000000001000101 ;
0=
b0101 A
#139
b0110 #
1=
b0000000001000110 >
#140
b0110 2
b0000000001000110 ;
0=
b0110 A
#141
b0111 #
1=
b0000000001000111 >
#142
b0111 2
b0000000001000111 ;
0=
b0111 A
#143
b1000 #
1=
b0000000001001000 >
#144
b1000 2
b0000000001001000 ;
0=
b1000 A
#145
b1001 #
1=
b0000000001001001 >
#146
b1001 2
b0000000001001001 ;
0=
b1001 A
#147
b1010 #
1=
b0000000001001010 >
#148
b1010 2
b0000000001001010 ;
0=
b1010 A
#149
b1011 #
1=
b0000000001001011 >
#150
b1011 2
b0000000001001011 ;
0=
b1011 A
#151
b1100 #
1=
b0000000001001100 >
#152
b1100 2
b0000000001001100 ;
0=
b1100 A
#153
b1101 #
1=
b0000000001001101 >
#154
b1101 2
b0000000001001101 ;
0=
b1101 A
#155
b1110 #
1=
b0000000001001110 >
#156
b1110 2
b0000000001001110 ;
0=
b1110 A
#157
b1111 #
1=
b0000000001001111 >
#158
0'
b1111 2
b0000000001001111 ;
0=
b1111 A
#159
b0000 #
b0101 $
1/
1=
b0000000001010000 >
#160
1'
0/
b0000 2
b0101 4
b0000000001010000 ;
0=
b0000 A
b0101 C
#161
b0001 #
1=
b0000000001010001 >
#162
b0001 2
b0000000001010001 ;
0=
b0001 A
#163
b0010 #
1=
b0000000001010010 >
#164
b0010 2
b0000000001010010 ;
0=
b0010 A
#165
b0011 #
1=
b0000000001010011 >
#166
b0011 2
b0000000001010011 ;
0=
b0011 A
#167
b0100 #
1=
b0000000001010100 >
#168
b0100 2
b0000000001010100 ;
0=
b0100 A
#169
b0101 #
1=
b0000000001010101 >
#170
b0101 2
b0000000001010101 ;
0=
b0101 A
#171
b0110 #
1=
b0000000001010110 >
#172
b0110 2
b0000000001010110 ;
0=
b0110 A
#173
b0111 #
1=
b0000000001010111 >
#174
b0111 2
b0000000001010111 ;
0=
b0111 A
#175
b1000 #
1=
b0000000001011000 >
#176
b1000 2
b0000000001011000 ;
0=
b1000 A
#177
b1001 #
1=
b0000000001011001 >
#178
b1001 2
b0000000001011001 ;
0=
b1001 A
#179
b1010 #
1=
b0000000001011010 >
#180
b1010 2
b0000000001011010 ;
0=
b1010 A
#181
b1011 #
1=
b0000000001011011 >
#182
b1011 2
b0000000001011011 ;
0=
b1011 A
#183
b1100 #
1=
b0000000001011100 >
#184
b1100 2
b0000000001011100 ;
0=
b1100 A
#185
b1101 #
1=
b0000000001011101 >
#186
b1101 2
b0000000001011101 ;
0=
b1101 A
#187
b1110 #
1=
b0000000001011110 >
#188
b1110 2
b0000000001011110 ;
0=
b1110 A
#189
b1111 #
1=
b0000000001011111 >
#190
0'
b1111 2
b0000000001011111 ;
0=
b1111 A
#191
b0000 #
b0110 $
1/
1=
b0000000001100000 >
#192
1'
0/
b0000 2
b0110 4
b0000000001100000 ;
0=
b0000 A
b0110 C
#193
b0001 #
1=
b0000000001100001 >
#194
b0001 2
b0000000001100001 ;
0=
b0001 A
#195
b0010 #
1=
b0000000001100010 >
#196
b0010 2
b0000000001100010 ;
0=
b0010 A
#197
b0011 #
1=
b0000000001100011 >
#198
b0011 2
b0000000001100011 ;
0=
b0011 A
#199
b0100 #
1=
b0000000001100100 >
#200
b0001 #
b0000 $
b0001 2
b0000 4
b0000000000000001 :
b0000000000000000 ;
0=
b0000000000000001 >
b0001 @
b0000 A
b0000 C
#201
b0010 #
1=
b0000000000000010 >
#202
b0001 3
b0000000000000001 ;
0=
b0001 A
#203
b0011 #
1=
b0000000000000011 >
#204
b0011 2
b0000 3
b0000000000000010 ;
0=
b0010 A
#205
b0100 #
1=
b0000000000000100 >
#206
b0001 3
b0000000000000011 ;
0=
b0011 A
#207
b0101 #
1=
b0000000000000101 >
#208
b0101 2
b0000 3
b0000000000000100 ;
0=
b0100 A
#209
b0110 #
1=
b0000000000000110 >
#210
b0001 3
b0000000000000101 ;
0=
b0101 A
#211
b0111 #
1=
b0000000000000111 >
#212
b0111 2
b0000 3
b0000000000000110 ;
0=
b0110 A
#213
b1000 #
1=
b0000000000001000 >
#214
b0001 3
b0000000000000111 ;
0=
b0111 A
#215
b1001 #
1=
b0000000000001001 >
#216
b1001 2
b0000 3
b0000000000001000 ;
0=
b1000 A
#217
b1010 #
1=
b0000000000001010 >
#218
b0001 3
b0000000000001001 ;
0=
b1001 A
#219
b1011 #
1=
b0000000000001011 >
#220
b1011 2
b0000 3
b0000000000001010 ;
0=
b1010 A
#221
b1100 #
1=
b0000000000001100 >
#222
b0001 3
b0000000000001011 ;
0=
b1011 A
#223
b1101 #
1=
b0000000000001101 >
#224
b1101 2
b0000 3
b0000000000001100 ;
0=
b1100 A
#225
b1110 #
1=
b0000000000001110 >
#226
b0001 3
b0000000000001101 ;
0=
b1101 A
#227
b1111 #
1=
b0000000000001111 >
#228
0'
b1111 2
b0000 3
b0000000000001110 ;
0=
b1110 A
#229
b0000 #
b0001 $
1/
1=
b0000000000010000 >
#230
0+
b0001 3
b0000000000001111 ;
0=
b1111 A
#231
b0001 #
1=
b0000000000010001 >
#232
1'
1+
0/
b0001 2
b0000 3
b0001 4
b0000000000010000 ;
0=
b0000 A
b0001 C
#233
b0010 #
1=
b0000000000010010 >
#234
b0001 3
b0000000000010001 ;
0=
b0001 A
#235
b0011 #
1=
b0000000000010011 >
#236
b0011 2
b0000 3
b0000000000010010 ;
0=
b0010 A
#237
b0100 #
1=
b0000000000010100 >
#238
b0001 3
b0000000000010011 ;
0=
b0011 A
#239
b0101 #
1=
b0000000000010101 >
#240
b0101 2
b0000 3
b0000000000010100 ;
0=
b0100 A
#241
b0110 #
1=
b0000000000010110 >
#242
b0001 3
b0000000000010101 ;
0=
b0101 A
#243
b0111 #
1=
b0000000000010111 >
#244
b0111 2
b0000 3
b0000000000010110 ;
0=
b0110 A
#245
b1000 #
1=
b0000000000011000 >
#246
b0001 3
b0000000000010111 ;
0=
b0111 A
#247
b1001 #
1=
b0000000000011001 >
#248
b1001 2
b0000 3
b0000000000011000 ;
0=
b1000 A
#249
b1010 #
1=
b0000000000011010 >
#250
b0001 3
b0000000000011001 ;
0=
b1001 A
#251
b1011 #
1=
b0000000000011011 >
#252
b1011 2
b0000 3
b0000000000011010 ;
0=
b1010 A
#253
b1100 #
1=
b0000000000011100 >
#254
b0001 3
b0000000000011011 ;
0=
b1011 A
#255
b1101 #
1=
b0000000000011101 >
#256
b1101 2
b0000 3
b0000000000011100 ;
0=
b1100 A
#257
b1110 #
1=
b0000000000011110 >
#258
b0001 3
b0000000000011101 ;
0=
b1101 A
#259
b1111 #
1=
b0000000000011111 >
#260
0'
b1111 2
b0000 3
b0000000000011110 ;
0=
b1110 A
#261
b0000 #
b0010 $
1/
1=
b0000000000100000 >
#262
0+
b0001 3
b0000000000011111 ;
0=
b1111 A
#263
b0001 #
1=
b0000000000100001 >
#264
1'
1+
0/
b0001 2
b0000 3
b0010 4
b0000000000100000 ;
0=
b0000 A
b0010 C
#265
b0010 #
1=
b0000000000100010 >
#266
b0001 3
b0000000000100001 ;
0=
b0001 A
#267
b0011 #
1=
b0000000000100011 >
#268
b0011 2
b0000 3
b0000000000100010 ;
0=
b0010 A
#269
b0100 #
1=
b0000000000100100 >
#270
b0001 3
b0000000000100011 ;
0=
b0011 A
#271
b0101 #
1=
b0000000000100101 >
#272
b0101 2
b0000 3
b0000000000100100 ;
0=
b0100 A
#273
b0110 #
1=
b0000000000100110 >
#274
b0001 3
b0000000000100101 ;
0=
b0101 A
#275
b0111 #
1=
b0000000000100111 >
#276
b0111 2
b0000 3
b0000000000100110 ;
0=
b0110 A
#277
b1000 #
1=
b0000000000101000 >
#278
b0001 3
b0000000000100111 ;
0=
b0111 A
#279
b1001 #
1=
b0000000000101001 >
#280
b1001 2
b0000 3
b0000000000101000 ;
0=
b1000 A
#281
b1010 #
1=
b0000000000101010 >
#282
b0001 3
b0000000000101001 ;
0=
b1001 A
#283
b1011 #
1=
b0000000000101011 >
#284
b1011 2
b0000 3
b0000000000101010 ;
0=
b1010 A
#285
b1100 #
1=
b0000000000101100 >
#286
b0001 3
b0000000000101011 ;
0=
b1011 A
#287
b1101 #
1=
b0000000000101101 >
#288
b1101 2
b0000 3
b0000000000101100 ;
0=
b1100 A
#289
b1110 #
1=
b0000000000101110 >
#290
b0001 3
b0000000000101101 ;
0=
b1101 A
#291
b1111 #
1=
b0000000000101111 >
#292
0'
b1111 2
b0000 3
b0000000000101110 ;
0=
b1110 A
#293
b0000 #
b0011 $
1/
1=
b0000000000110000 >
#294
0+
b0001 3
b0000000000101111 ;
0=
b1111 A
#295
b0001 #
1=
b0000000000110001 >
#296
1'
1+
0/
b0001 2
b0000 3
b0011 4
b0000000000110000 ;
0=
b0000 A
b0011 C
#297
b0010 #
1=
b0000000000110010 >
#298
b0001 3
b0000000000110001 ;
0=
b0001 A
#299
b0011 #
1=
b0000000000110011 >
#300
b0011 2
b0000 3
b0000000000110010 ;
0=
b0010 A
#301
b0100 #
1=
b0000000000110100 >
#302
b0001 3
b0000000000110011 ;
0=
b0011 A
#303
b0101 #
1=
b0000000000110101 >
#304
b0101 2
b0000 3
b0000000000110100 ;
0=
b0100 A
#305
b0110 #
1=
b0000000000110110 >
#306
b0001 3
b0000000000110101 ;
0=
b0101 A
#307
b0111 #
1=
b0000000000110111 >
#308
b0111 2
b0000 3
b0000000000110110 ;
0=
b0110 A
#309
b1000 #
1=
b0000000000111000 >
#310
b0001 3
b0000000000110111 ;
0=
b0111 A
#311
b1001 #
1=
b0000000000111001 >
#312
b1001 2
b0000 3
b0000000000111000 ;
0=
b1000 A
#313
b1010 #
1=
b0000000000111010 >
#314
b0001 3
b0000000000111001 ;
0=
b1001 A
#315
b1011 #
1=
b0000000000111011 >
#316
b1011 2
b0000 3
b0000000000111010 ;
0=
b1010 A
#317
b1100 #
1=
b0000000000111100 >
#318
b0001 3
b0000000000111011 ;
0=
b1011 A
#319
b1101 #
1=
b0000000000111101 >
#320
b1101 2
b0000 3
b0000000000111100 ;
0=
b1100 A
#321
b1110 #
1=
b0000000000111110 >
#322
b0001 3
b0000000000111101 ;
0=
b1101 A
#323
b1111 #
1=
b0000000000111111 >
#324
0'
b1111 2
b0000 3
b0000000000111110 ;
0=
b1110 A
#325
b0000 #
b0100 $
1/
1=
b0000000001000000 >
#326
0+
b0001 3
b0000000000111111 ;
0=
b1111 A
#327
b0001 #
1=
b0000000001000001 >
#328
1'
1+
0/
b0001 2
b0000 3
b0100 4
b0000000001000000 ;
0=
b0000 A
b0100 C
#329
b0010 #
1=
b0000000001000010 >
#330
b0001 3
b0000000001000001 ;
0=
b0001 A
#331
b0011 #
1=
b0000000001000011 >
#332
b0011 2
b0000 3
b0000000001000010 ;
0=
b0010 A
#333
b0100 #
1=
b0000000001000100 >
#334
b0001 3
b0000000001000011 ;
0=
b0011 A
#335
b0101 #
1=
b0000000001000101 >
#336
b0101 2
b0000 3
b0000000001000100 ;
0=
b0100 A
#337
b0110 #
1=
b0000000001000110 >
#338
b0001 3
b0000000001000101 ;
0=
b0101 A
#339
b0111 #
1=
b0000000001000111 >
#340
b0111 2
b0000 3
b0000000001000110 ;
0=
b0110 A
#341
b1000 #
1=
b0000000001001000 >
#342
b0001 3
b0000000001000111 ;
0=
b0111 A
#343
b1001 #
1=
b0000000001001001 >
#344
b1001 2
b0000 3
b0000000001001000 ;
0=
b1000 A
#345
b1010 #
1=
b0000000001001010 >
#346
b0001 3
b0000000001001001 ;
0=
b1001 A
#347
b1011 #
1=
b0000000001001011 >
#348
b1011 2
b0000 3
b0000000001001010 ;
0=
b1010 A
#349
b1100 #
1=
b0000000001001100 >
#350
b0001 3
b0000000001001011 ;
0=
b1011 A
#351
b1101 #
1=
b0000000001001101 >
#352
b1101 2
b0000 3
b0000000001001100 ;
0=
b1100 A
#353
b1110 #
1=
b0000000001001110 >
#354
b0001 3
b0000000001001101 ;
0=
b1101 A
#355
b1111 #
1=
b0000000001001111 >
#356
0'
b1111 2
b0000 3
b0000000001001110 ;
0=
b1110 A
#357
b0000 #
b0101 $
1/
1=
b0000000001010000 >
#358
0+
b0001 3
b0000000001001111 ;
0=
b1111 A
#359
b0001 #
1=
b0000000001010001 >
#360
1'
1+
0/
b0001 2
b0000 3
b0101 4
b0000000001010000 ;
0=
b0000 A
b0101 C
#361
b0010 #
1=
b0000000001010010 >
#362
b0001 3
b0000000001010001 ;
0=
b0001 A
#363
b0011 #
1=
b0000000001010011 >
#364
b0011 2
b0000 3
b0000000001010010 ;
0=
b0010 A
#365
b0100 #
1=
b0000000001010100 >
#366
b0001 3
b0000000001010011 ;
0=
b0011 A
#367
b0101 #
1=
b0000000001010101 >
#368
b0101 2
b0000 3
b0000000001010100 ;
0=
b0100 A
#369
b0110 #
1=
b0000000001010110 >
#370
b0001 3
b0000000001010101 ;
0=
b0101 A
#371
b0111 #
1=
b0000000001010111 >
#372
b0111 2
b0000 3
b0000000001010110 ;
0=
b0110 A
#373
b1000 #
1=
b0000000001011000 >
#374
b0001 3
b0000000001010111 ;
0=
b0111 A
#375
b1001 #
1=
b0000000001011001 >
#376
b1001 2
b0000 3
b0000000001011000 ;
0=
b1000 A
#377
b1010 #
1=
b0000000001011010 >
#378
b0001 3
b0000000001011001 ;
0=
b1001 A
#379
b1011 #
1=
b0000000001011011 >
#380
b1011 2
b0000 3
b0000000001011010 ;
0=
b1010 A
#381
b1100 #
1=
b0000000001011100 >
#382
b0001 3
b0000000001011011 ;
0=
b1011 A
#383
b1101 #
1=
b0000000001011101 >
#384
b1101 2
b0000 3
b0000000001011100 ;
0=
b1100 A
#385
b1110 #
1=
b0000000001011110 >
#386
b0001 3
b0000000001011101 ;
0=
b1101 A
#387
b1111 #
1=
b0000000001011111 >
#388
0'
b1111 2
b0000 3
b0000000001011110 ;
0=
b1110 A
#389
b0000 #
b0110 $
1/
1=
b0000000001100000 >
#390
0+
b0001 3
b0000000001011111 ;
0=
b1111 A
#391
b0001 #
1=
b0000000001100001 >
#392
1'
1+
0/
b0001 2
b0000 3
b0110 4
b0000000001100000 ;
0=
b0000 A
b0110 C
#393
b0010 #
1=
b0000000001100010 >
#394
b0001 3
b0000000001100001 ;
0=
b0001 A
#395
b0011 #
1=
b0000000001100011 >
#396
b0011 2
b0000 3
b0000000001100010 ;
0=
b0010 A
#397
b0100 #
1=
b0000000001100100 >
#398
b0001 3
b0000000001100011 ;
0=
b0011 A
#399
b0101 #
1=
b0000000001100101 >
#400
b0010 #
b0000 $
b0010 2
b0000 3
b0000 4
b0000000000000010 :
b0000000000000000 ;
0=
b0000000000000010 >
b0010 @
b0000 A
b0000 C
#401
b0011 #
1=
b0000000000000011 >
#402
b0011 2
b0000000000000001 ;
0=
b0001 A
#403
b0100 #
1=
b0000000000000100 >
#404
b0010 2
b0010 3
b0000000000000010 ;
0=
b0010 A
#405
b0101 #
1=
b0000000000000101 >
#406
b0011 2
b0000000000000011 ;
0=
b0011 A
#407
b0110 #
1=
b0000000000000110 >
#408
b0110 2
b0000 3
b0000000000000100 ;
0=
b0100 A
#409
b0111 #
1=
b0000000000000111 >
#410
b0111 2
b0000000000000101 ;
0=
b0101 A
#411
b1000 #
1=
b0000000000001000 >
#412
b0110 2
b0010 3
b0000000000000110 ;
0=
b0110 A
#413
b1001 #
1=
b0000000000001001 >
#414
b0111 2
b0000000000000111 ;
0=
b0111 A
#415
b1010 #
1=
b0000000000001010 >
#416
b1010 2
b0000 3
b0000000000001000 ;
0=
b1000 A
#417
b1011 #
1=
b0000000000001011 >
#418
b1011 2
b0000000000001001 ;
0=
b1001 A
#419
b1100 #
1=
b0000000000001100 >
#420
b1010 2
b0010 3
b0000000000001010 ;
0=
b1010 A
#421
b1101 #
1=
b0000000000001101 >
#422
b1011 2
b0000000000001011 ;
0=
b1011 A
#423
b1110 #
1=
b0000000000001110 >
